{
  "created": 1446377734080,
  "character": "Christie",
  "children": [
    {
      "name": "STD",
      "children": [
        {
          "input": "P",
          "children": [
            {
              "input": "P",
              "children": [
                {
                  "input": "P",
                  "children": [
                    {
                      "input": "P",
                      "children": [
                        {
                          "input": "P"
                        },
                        {
                          "input": "2P"
                        },
                        {
                          "input": "2P+K",
                          "endsWith": "JKH"
                        },
                        {
                          "input": "8P+K",
                          "endsWith": "JKH"
                        }
                      ]
                    }
                  ]
                },
                {
                  "input": "4P",
                  "endsWith": "BT",
                  "children": [
                    {
                      "input": "P",
                      "children": [
                        {
                          "input": "(P)",
                          "children": [
                            {
                              "input": "8",
                              "endsWith": "JKH"
                            },
                            {
                              "input": "2",
                              "endsWith": "JKH"
                            },
                            {
                              "input": "P"
                            }
                          ]
                        }
                      ]
                    },
                    {
                      "input": "K",
                      "children": [
                        {
                          "input": "P"
                        }
                      ]
                    },
                    {
                      "input": "2K"
                    }
                  ]
                },
                {
                  "input": "2P",
                  "children": [
                    {
                      "input": "P"
                    }
                  ]
                },
                {
                  "input": "K",
                  "children": [
                    {
                      "input": "K"
                    }
                  ]
                },
                {
                  "input": "2K",
                  "children": [
                    {
                      "input": "P"
                    },
                    {
                      "input": "T"
                    }
                  ]
                }
              ]
            },
            {
              "input": "K",
              "children": [
                {
                  "input": "K",
                  "children": [
                    {
                      "input": "K"
                    },
                    {
                      "input": "2K"
                    },
                    {
                      "input": "8P+K",
                      "endsWith": "JKH"
                    },
                    {
                      "input": "2P+K",
                      "endsWith": "JKH"
                    }
                  ]
                }
              ]
            }
          ]
        },
        {
          "input": "9P"
        },
        {
          "input": "8P",
          "children": [
            {
              "input": "P"
            }
          ]
        },
        {
          "input": "7P",
          "children": [
            {
              "input": "P",
              "children": [
                {
                  "input": "P"
                }
              ]
            }
          ]
        },
        {
          "input": "6P",
          "children": [
            {
              "input": "P",
              "children": [
                {
                  "input": "P",
                  "children": [
                    {
                      "input": "P"
                    }
                  ]
                },
                {
                  "input": "8P+K",
                  "endsWith": "JKH"
                },
                {
                  "input": "2P+K",
                  "endsWith": "JKH"
                }
              ]
            }
          ]
        },
        {
          "input": "4P",
          "endsWith": "BT",
          "children": [
            {
              "input": "P",
              "children": [
                {
                  "input": "(P)",
                  "children": [
                    {
                      "input": "8",
                      "endsWith": "JKH"
                    },
                    {
                      "input": "2",
                      "endsWith": "JKH"
                    },
                    {
                      "input": "P"
                    }
                  ]
                }
              ]
            },
            {
              "input": "K",
              "children": [
                {
                  "input": "P"
                }
              ]
            },
            {
              "input": "2K"
            }
          ]
        },
        {
          "input": "3P",
          "children": [
            {
              "input": "P",
              "children": [
                {
                  "input": "(P)",
                  "children": [
                    {
                      "input": "8",
                      "endsWith": "JKH"
                    },
                    {
                      "input": "2",
                      "endsWith": "JKH"
                    },
                    {
                      "input": "P"
                    }
                  ]
                }
              ]
            }
          ]
        },
        {
          "input": "(3)P"
        },
        {
          "input": "2P",
          "children": [
            {
              "input": "P",
              "children": [
                {
                  "input": "P"
                }
              ]
            }
          ]
        },
        {
          "input": "1P",
          "children": [
            {
              "input": "K"
            }
          ]
        },
        {
          "input": "66P",
          "children": [
            {
              "input": "P",
              "children": [
                {
                  "input": "(P)",
                  "children": [
                    {
                      "input": "8",
                      "endsWith": "JKH"
                    },
                    {
                      "input": "2",
                      "endsWith": "JKH"
                    },
                    {
                      "input": "P"
                    }
                  ]
                }
              ]
            }
          ]
        },
        {
          "input": "46P"
        },
        {
          "input": "33P"
        },
        {
          "input": "236P"
        },
        {
          "input": "214P"
        },
        {
          "input": "K",
          "children": [
            {
              "input": "P"
            },
            {
              "input": "K",
              "children": [
                {
                  "input": "K"
                },
                {
                  "input": "2K"
                },
                {
                  "input": "8P+K",
                  "endsWith": "JKH"
                },
                {
                  "input": "2P+K",
                  "endsWith": "JKH"
                }
              ]
            }
          ]
        },
        {
          "input": "9K",
          "children": [
            {
              "input": "K"
            }
          ]
        },
        {
          "input": "8K"
        },
        {
          "input": "7K"
        },
        {
          "input": "6K",
          "children": [
            {
              "input": "P"
            },
            {
              "input": "K"
            },
            {
              "input": "4K",
              "endsWith": "BT",
              "context": [
                "AIR"
              ]
            },
            {
              "input": "8P+K",
              "endsWith": "JKH"
            },
            {
              "input": "2P+K",
              "endsWith": "JKH"
            }
          ]
        },
        {
          "input": "4K",
          "children": [
            {
              "input": "K"
            },
            {
              "input": "2K",
              "children": [
                {
                  "input": "P",
                  "children": [
                    {
                      "input": "P"
                    },
                    {
                      "input": "2P"
                    }
                  ]
                }
              ]
            }
          ]
        },
        {
          "input": "3K",
          "children": [
            {
              "input": "P"
            },
            {
              "input": "K"
            },
            {
              "input": "8P+K",
              "endsWith": "JKH"
            },
            {
              "input": "2P+K",
              "endsWith": "JKH"
            }
          ]
        },
        {
          "input": "2K"
        },
        {
          "input": "1K",
          "children": [
            {
              "input": "P",
              "children": [
                {
                  "input": "P"
                },
                {
                  "input": "2P"
                }
              ]
            }
          ]
        },
        {
          "input": "66K",
          "endsWith": "BT"
        },
        {
          "input": "2K",
          "context": [
            "RUN"
          ]
        },
        {
          "input": "P+K"
        },
        {
          "input": "6P+K"
        },
        {
          "input": "3P+K",
          "endsWith": "ROLL"
        },
        {
          "input": "4P+K",
          "children": [
            {
              "input": "(3)",
              "endsWith": "ROLL"
            }
          ]
        },
        {
          "input": "1(P+K)"
        },
        {
          "input": "214(P+K)"
        },
        {
          "input": "H+K",
          "children": [
            {
              "input": "K",
              "children": [
                {
                  "input": "K"
                }
              ]
            }
          ]
        },
        {
          "input": "6H+K",
          "endsWith": "BT"
        },
        {
          "input": "4H+K",
          "endsWith": "BT"
        },
        {
          "input": "2H+K",
          "children": [
            {
              "input": "P"
            },
            {
              "input": "T"
            }
          ]
        }
      ]
    }
  ]
}